apoc/__init__.py
apoc/_converter.py
apoc/_feature_sets.py
apoc/_object_classifier.py
apoc/_object_merger.py
apoc/_object_segmenter.py
apoc/_object_selector.py
apoc/_pixel_classifier.py
apoc/_probability_mapper.py
apoc/_table_row_classifier.py
apoc/_utils.py
apoc-0.12.0.dist-info/LICENSE
apoc-0.12.0.dist-info/METADATA
apoc-0.12.0.dist-info/WHEEL
apoc-0.12.0.dist-info/top_level.txt
apoc-0.12.0.dist-info/RECORD
