Metadata-Version: 2.1
Name: apoc
Version: 0.12.0
Summary: Accelerated Pixel and Object Classifiers based on OpenCL
Home-page: https://github.com/haesleinhuepf/apoc
Author: haesleinhuepf
Author-email: robert.haase@tu-dresden.de
Classifier: Programming Language :: Python :: 3
Classifier: License :: OSI Approved :: BSD License
Classifier: Operating System :: OS Independent
Classifier: Intended Audience :: Science/Research
Classifier: Development Status :: 3 - Alpha
Requires-Python: >=3.6
License-File: LICENSE
Requires-Dist: numpy (>=1.21)
Requires-Dist: scikit-learn (>=0.24.2)
Requires-Dist: pyclesperanto-prototype (>=0.21.1)
Requires-Dist: pandas
